{
  "canvases": [
    {
      "id": 5,
      "title": "혁신적인 스마트홈 솔루션!!",
      "lastModified": "2023-08-22",
      "category": "신규",
      "problem": {
        "notes": [
          {
            "id": "c280b19c-ebd2-4a81-8e39-72b925c3ab27",
            "content": "한글입력",
            "color": "bg-yellow-300"
          },
          {
            "id": "8f722268-3667-4209-82e8-22d20ed01ab3",
            "content": "",
            "color": ""
          }
        ]
      },
      "customerSegments": {
        "notes": [
          {
            "id": "cs1",
            "content": "30-50대 중산층 가정ㅇㅇㅇㄴㅇㄹㄴㅇㄹ",
            "color": "bg-blue-300"
          },
          {
            "id": "cs2",
            "content": "기술에 관심 있는 밀레니얼 세대",
            "color": "bg-yellow-300"
          },
          {
            "id": "cs3",
            "content": "에너지 절약에 관심 있는 환경 의식적 소비자",
            "color": "bg-pink-300"
          }
        ]
      },
      "valueProposition": {
        "notes": [
          {
            "id": "vp1",
            "content": "직관적이고 사용하기 쉬운 인터페이스sdsddsdㄴㄴㅇㄹddsdsdsdfsdfsdfsdfsdfsdfㅇㄹㄴㅇㄹㄴㅇㄹ",
            "color": "bg-pink-300"
          },
          {
            "id": "vp2",
            "content": "저렴한 초기 비용과 월 구독 모델",
            "color": "bg-yellow-300"
          },
          {
            "id": "vp3",
            "content": "모든 주요 스마트홈 기기와 호환",
            "color": "bg-blue-300"
          }
        ]
      },
      "solution": {
        "notes": [
          {
            "id": "s2",
            "content": "클라우드 기반 중앙 제어 시스템",
            "color": "bg-blue-300"
          },
          {
            "id": "s3",
            "content": "모듈식 설계로 쉬운 확장성 ㅎㅏㄴㄱㅡㄹ",
            "color": "bg-pink-300"
          }
        ]
      },
      "unfairAdvantage": {
        "notes": [
          {
            "id": "ua1",
            "content": "특허받은 AI 알ㅇㅇdㄴㅇㄹㄴㅇㄹㄴㅇㄹ",
            "color": "bg-pink-300"
          },
          {
            "id": "ua2",
            "content": "주요 스마트홈 기기 제조업체와의 독점 파트너십",
            "color": "bg-yellow-300"
          }
        ]
      },
      "channels": {
        "notes": [
          {
            "id": "ch1",
            "content": "온라인 직접 판매",
            "color": "bg-yellow-300"
          },
          {
            "id": "ch2",
            "content": "전문 설치 업체 네트워크",
            "color": "bg-blue-300"
          },
          {
            "id": "ch3",
            "content": "대형 전자제품 소매점",
            "color": "bg-pink-300"
          }
        ]
      },
      "keyMetrics": {
        "notes": [
          {
            "id": "km1",
            "content": "월간 활성 사용자 수",
            "color": "bg-blue-300"
          },
          {
            "id": "km2",
            "content": "고객 유지율",
            "color": "bg-yellow-300"
          },
          {
            "id": "km3",
            "content": "평균 에너지 절감률",
            "color": "bg-pink-300"
          }
        ]
      },
      "costStructure": {
        "notes": [
          {
            "id": "cs1",
            "content": "하드웨어 개발 및 생산 비용",
            "color": "bg-pink-300"
          },
          {
            "id": "cs2",
            "content": "소프트웨어 개발 및 유지보수",
            "color": "bg-blue-300"
          },
          {
            "id": "cs3",
            "content": "마케팅 및 고객 지원",
            "color": "bg-yellow-300"
          }
        ]
      },
      "revenueStreams": {
        "notes": [
          {
            "id": "rs1",
            "content": "하드웨어 판매",
            "color": "bg-yellow-300"
          },
          {
            "id": "rs2",
            "content": "월간 구독료",
            "color": "bg-pink-300"
          },
          {
            "id": "rs3",
            "content": "프리미엄 기능 업그레이드",
            "color": "bg-blue-300"
          }
        ]
      },
      "existingAlternatives": {
        "notes": [
          {
            "id": "ea1",
            "content": "기존 홈 오토메이션 시스템",
            "color": "bg-yellow-300"
          },
          {
            "id": "ea2",
            "content": "개별 스마트 기기 사용",
            "color": "bg-pink-300"
          }
        ]
      },
      "highLevelConcept": {
        "notes": [
          {
            "id": "hlc1",
            "content": "모든 가정을 위한 AI 기반 스마트홈",
            "color": "bg-blue-300"
          }
        ]
      },
      "earlyAdopters": {
        "notes": [
          {
            "id": "ea1",
            "content": "테크 얼리어답터",
            "color": "bg-blue-300"
          },
          {
            "id": "ea2",
            "content": "에너지 절약 열성 지지자",
            "color": "bg-pink-300"
          }
        ]
      }
    },
    {
      "title": "37e2_new Lean Canvas",
      "lastModified": "2025-07-31 13:38:30",
      "category": "Category",
      "id": 7
    },
    {
      "title": "e6d0_new Lean Canvas",
      "lastModified": "2025-07-31 14:19:41",
      "category": "Category",
      "id": 8
    },
    {
      "title": "9880_new Lean Canvas",
      "lastModified": "2025-07-31 14:19:43",
      "category": "Category",
      "id": 9
    },
    {
      "title": "d3f9_new Lean Canvas",
      "lastModified": "2025-07-31 14:19:44",
      "category": "Category",
      "id": 10
    },
    {
      "title": "70b7_new Lean Canvas",
      "lastModified": "2025-07-31 14:20:07",
      "category": "Category",
      "id": 11
    },
    {
      "title": "a775_new Lean Canvas",
      "lastModified": "2025-07-31 14:20:09",
      "category": "Category",
      "id": 12
    },
    {
      "title": "464c_new Lean Canvas",
      "lastModified": "2025-07-31 14:25:07",
      "category": "신규",
      "id": 13
    },
    {
      "title": "acb5_new Lean Canvas",
      "lastModified": "2025-07-31 14:25:08",
      "category": "신규",
      "id": 14
    }
  ]
}